emicroml/__init__.py
emicroml/version.py
emicroml/modelling/__init__.py
emicroml/modelling/_common.py
emicroml/modelling/optimizers.py
emicroml/modelling/cbed/__init__.py
emicroml/modelling/cbed/distortion/__init__.py
emicroml/modelling/cbed/distortion/_common.py
emicroml/modelling/cbed/distortion/estimation.py
emicroml/modelling/lr/__init__.py
emicroml/modelling/lr/schedulers.py
emicroml-0.0.6.dist-info/licenses/LICENSE
emicroml-0.0.6.dist-info/METADATA
emicroml-0.0.6.dist-info/WHEEL
emicroml-0.0.6.dist-info/top_level.txt
emicroml-0.0.6.dist-info/RECORD
