Metadata-Version: 2.4
Name: emicroml
Version: 0.0.6
Summary: A Python library for training machine learning models for applications in electron microscopy.
Author-email: Matthew Fitzpatrick <matthew.rc.fitzpatrick@gmail.com>
Project-URL: Homepage, https://mrfitzpa.github.io/emicroml
Project-URL: Repository, https://github.com/mrfitzpa/emicroml
Keywords: pytorch,electron microscopy,microscopy,diffraction,cbed,saed,distortion measurement,distortion correction,machine learning,deep learning,gpu
Classifier: License :: OSI Approved :: GNU General Public License v3 (GPLv3)
Classifier: Development Status :: 5 - Production/Stable
Classifier: Intended Audience :: Science/Research
Classifier: Programming Language :: Python
Classifier: Programming Language :: Python :: 3
Classifier: Programming Language :: Python :: 3.9
Classifier: Programming Language :: Python :: 3.10
Classifier: Programming Language :: Python :: 3.11
Classifier: Programming Language :: Python :: 3.12
Classifier: Operating System :: OS Independent
Classifier: Natural Language :: English
Requires-Python: >=3.9
License-File: LICENSE
Requires-Dist: fakecbed>=0.3.6
Requires-Dist: empix>=0.0.6
Requires-Dist: kornia
Requires-Dist: h5pywrappers
Provides-Extra: tests
Requires-Dist: pytest-cov; extra == "tests"
Provides-Extra: examples
Requires-Dist: jupyter; extra == "examples"
Requires-Dist: ipympl; extra == "examples"
Requires-Dist: pyopencl[pocl]; extra == "examples"
Requires-Dist: prismatique; extra == "examples"
Provides-Extra: docs
Requires-Dist: sphinx<7; extra == "docs"
Requires-Dist: sphinx_rtd_theme; extra == "docs"
Requires-Dist: sphinx-autodoc-typehints; extra == "docs"
Requires-Dist: numpydoc; extra == "docs"
Requires-Dist: docutils; extra == "docs"
Provides-Extra: all
Requires-Dist: emicroml[docs,examples,tests]; extra == "all"
Dynamic: license-file
